remnawave_api/.DS_Store
remnawave_api/__init__.py
remnawave_api/controllers/__init__.py
remnawave_api/controllers/api_tokens_management.py
remnawave_api/controllers/auth.py
remnawave_api/controllers/bandwidthstats.py
remnawave_api/controllers/hosts.py
remnawave_api/controllers/hosts_bulk_actions.py
remnawave_api/controllers/hwid.py
remnawave_api/controllers/inbounds.py
remnawave_api/controllers/inbounds_bulk_actions.py
remnawave_api/controllers/keygen.py
remnawave_api/controllers/nodes.py
remnawave_api/controllers/subscription.py
remnawave_api/controllers/subscriptions_settings.py
remnawave_api/controllers/subscriptions_template.py
remnawave_api/controllers/system.py
remnawave_api/controllers/users.py
remnawave_api/controllers/users_bulk_actions.py
remnawave_api/controllers/users_stats.py
remnawave_api/controllers/webhooks.py
remnawave_api/controllers/xray_config.py
remnawave_api/enums/__init__.py
remnawave_api/enums/alpn.py
remnawave_api/enums/client_type.py
remnawave_api/enums/error_code.py
remnawave_api/enums/fingerprint.py
remnawave_api/enums/security_layer.py
remnawave_api/enums/template_type.py
remnawave_api/enums/users.py
remnawave_api/exceptions/__init__.py
remnawave_api/exceptions/general.py
remnawave_api/exceptions/handler.py
remnawave_api/models/__init__.py
remnawave_api/models/api_tokens_management.py
remnawave_api/models/auth.py
remnawave_api/models/bandwidthstats.py
remnawave_api/models/hosts.py
remnawave_api/models/hosts_bulk_actions.py
remnawave_api/models/hwid.py
remnawave_api/models/inbounds.py
remnawave_api/models/inbounds_bulk_actions.py
remnawave_api/models/keygen.py
remnawave_api/models/nodes.py
remnawave_api/models/subscription.py
remnawave_api/models/subscriptions_settings.py
remnawave_api/models/subscriptions_template.py
remnawave_api/models/system.py
remnawave_api/models/users.py
remnawave_api/models/users_bulk_actions.py
remnawave_api/models/users_stats.py
remnawave_api/models/xray_config.py
remnawave_api/rapid/__init__.py
remnawave_api-1.1.2.dist-info/LICENSE
remnawave_api-1.1.2.dist-info/METADATA
remnawave_api-1.1.2.dist-info/WHEEL
remnawave_api-1.1.2.dist-info/RECORD
