Metadata-Version: 2.3
Name: remnawave-api
Version: 1.1.2
Summary: A Python SDK for interacting with the Remnawave API.
License: MIT
Keywords: remnawave,api,sdk,proxy,httpx,async,xray
Author: Artem
Author-email: sm1ky@forestsnet.com
Requires-Python: >=3.11,<4.0
Classifier: Development Status :: 5 - Production/Stable
Classifier: Intended Audience :: Developers
Classifier: License :: OSI Approved :: MIT License
Classifier: Natural Language :: English
Classifier: Programming Language :: Python :: 3.11
Classifier: Programming Language :: Python :: 3.12
Classifier: Programming Language :: Python :: 3.13
Classifier: Programming Language :: Python :: Implementation :: CPython
Classifier: Programming Language :: Python :: Implementation :: PyPy
Classifier: Framework :: AsyncIO
Requires-Dist: httpx (>=0.27.2,<0.28.0)
Requires-Dist: orjson (>=3.10.15,<4.0.0)
Requires-Dist: pydantic (>=2.9.2,<3.0.0)
Requires-Dist: pydantic-core (>=2.33.1,<2.34.0)
Requires-Dist: pydantic[email] (>=2.9.2,<3.0.0)
Requires-Dist: rapid-api-client (==0.6.0)
Project-URL: Community Chat, https://t.me/+xQs17zMzwCY1NzYy
Project-URL: Developer, https://t.me/forests_dev
Project-URL: Homepage, https://github.com/sm1ky/remnawave-api
Project-URL: Panel Page, https://remna.st/
Project-URL: Update Channel, https://t.me/remnawave
